felimination/__init__.py
felimination/callbacks.py
felimination/drift.py
felimination/ga.py
felimination/importance.py
felimination/rfe.py
felimination-0.5.0.dist-info/licenses/LICENSE
felimination-0.5.0.dist-info/WHEEL
felimination-0.5.0.dist-info/METADATA
felimination-0.5.0.dist-info/RECORD
