Metadata-Version: 2.4
Name: felimination
Version: 0.5.0
Summary: This library contains some useful scikit-learn compatible classes for feature selection.
Keywords: feature selection,scikit-learn,machine learning
Author-email: Claudio Salvatore Arcidiacono <author@email.com>
Requires-Python: >=3.10
Classifier: Programming Language :: Python :: 3
Classifier: License :: OSI Approved :: MIT License
Classifier: Operating System :: OS Independent
License-File: LICENSE
Requires-Dist: scikit-learn>=1.6.1,<2.0.0
Requires-Dist: pandas>=2.1.0,<4.0.0
Requires-Dist: seaborn>=0.11.1,<1.0.0
Project-URL: Bug Tracker, https://github.com/ClaudioSalvatoreArcidiacono/felimination/issues
Project-URL: Documentation, https://claudiosalvatorearcidiacono.github.io/felimination/
Project-URL: Homepage, https://github.com/ClaudioSalvatoreArcidiacono/felimination
